{
    "orders": [
        {
            "contact-info": {
                "name": "John Smith",
                "email": "jsmith@microsoft.com"
            },
            "order-info": {
                "orderId": "9",
                "itemId": "101",
                "item-desc": "TV",
                "quantity": "1",
                "price": "1000"
            }
        },
        {
            "contact-info": {
                "name": "Sarah Connor",
                "email": "sconner123@gmail.com"
            },
            "order-info": {
                "orderId": "10",
                "itemId": "101",
                "item-desc": "TV",
                "quantity": "1",
                "price": "1000"
            }
        }
    ]
}